{"name":"Follownext-safari","body":"# Follow Next Safari Extension\r\n\r\n Creates a keybinding allowing you to follow links that look like \"next\" or\r\n \"previous\" links.\r\n\r\n## Installation\r\n\r\n- Double click Safari extension bundle. Configure patterns (if desired) in preferences.\r\n\r\n## Usage\r\n\r\n- Press ^ ← *(ctrl-left)* for following 'previous' links\r\n- Press ^ → *(ctrl-right)* for following 'next' links\r\n\r\nWorks for most sane page layouts, e.g.:\r\n\r\n- Google search results\r\n- Google issues, groups\r\n- Most generic forums pagination\r\n- Last fm comment boxes\r\n\r\nPatterns can be tweaked in preferences to accommodate different cases.\r\n\r\n## Screenshots\r\n\r\n![Follow next](https://github.com/gaving/follownext-safari/raw/master/site/1.png)\r\n\r\n## Credit\r\n\r\nRipped some code from [vimperator](http://vimperator.org/) and plugin layout ideas from the\r\nawesome [type to navigate](http://dbergey.github.com/) Safari extension.\r\n\r\n## Contact\r\n\r\n[@vesech](http://twitter.com/vesech/) on Twitter.","tagline":"Follow links which look like \"next\" and \"previous\" with ^ → and ^ ←","google":"","note":"Don't delete this file! It's used internally to help with page regeneration."}